{
    "suggestion_groups": [
        {
            "suggestion": "block 1: 1, low-level: (1, -1), block 2: 3, low-level: (-1, -1)",
            "symbol": "triangle-down"
        },
        {
            "suggestion": "high-level: (-1, -1, 1, 1)",
            "symbol": "triangle-up"
        }
    ],
    "landscape": {
        "id": 58,
        "block_nr1": 1,
        "block_nr2": 3,
        "coefficients_low": [
            0.23093783880016316,
            -0.164428722902522,
            0.20841028506013373,
            0.1698965837664983,
            0.28663053923632537,
            0.4054101169682215,
            0.29275851715528156,
            -0.19744845493574076
        ],
        "coefficients_high": [
            0.4261094204989445,
            -0.43547518006037705,
            0.12419299328020562,
            -0.37046577010503995
        ],
        "combinations": [
            {
                "combination": "(-1, -1, -1, -1, -1, -1, -1, -1)",
                "reward": 61.0
            },
            {
                "combination": "(-1, -1, -1, -1, -1, -1, -1, 1)",
                "reward": 70.0
            },
            {
                "combination": "(-1, -1, -1, -1, -1, -1, 1, -1)",
                "reward": 96.0
            },
            {
                "combination": "(-1, -1, -1, -1, -1, -1, 1, 1)",
                "reward": 66.0
            },
            {
                "combination": "(-1, -1, -1, -1, -1, 1, -1, -1)",
                "reward": 76.0
            },
            {
                "combination": "(-1, -1, -1, -1, -1, 1, -1, 1)",
                "reward": 85.0
            },
            {
                "combination": "(-1, -1, -1, -1, -1, 1, 1, -1)",
                "reward": 111.0
            },
            {
                "combination": "(-1, -1, -1, -1, -1, 1, 1, 1)",
                "reward": 81.0
            },
            {
                "combination": "(-1, -1, -1, -1, 1, -1, -1, -1)",
                "reward": 69.0
            },
            {
                "combination": "(-1, -1, -1, -1, 1, -1, -1, 1)",
                "reward": 79.0
            },
            {
                "combination": "(-1, -1, -1, -1, 1, -1, 1, -1)",
                "reward": 104.0
            },
            {
                "combination": "(-1, -1, -1, -1, 1, -1, 1, 1)",
                "reward": 74.0
            },
            {
                "combination": "(-1, -1, -1, -1, 1, 1, -1, -1)",
                "reward": 97.0
            },
            {
                "combination": "(-1, -1, -1, -1, 1, 1, -1, 1)",
                "reward": 106.0
            },
            {
                "combination": "(-1, -1, -1, -1, 1, 1, 1, -1)",
                "reward": 132.0
            },
            {
                "combination": "(-1, -1, -1, -1, 1, 1, 1, 1)",
                "reward": 102.0
            },
            {
                "combination": "(-1, -1, -1, 1, -1, -1, -1, -1)",
                "reward": 93.0
            },
            {
                "combination": "(-1, -1, -1, 1, -1, -1, -1, 1)",
                "reward": 102.0
            },
            {
                "combination": "(-1, -1, -1, 1, -1, -1, 1, -1)",
                "reward": 128.0
            },
            {
                "combination": "(-1, -1, -1, 1, -1, -1, 1, 1)",
                "reward": 98.0
            },
            {
                "combination": "(-1, -1, -1, 1, -1, 1, -1, -1)",
                "reward": 107.0
            },
            {
                "combination": "(-1, -1, -1, 1, -1, 1, -1, 1)",
                "reward": 117.0
            },
            {
                "combination": "(-1, -1, -1, 1, -1, 1, 1, -1)",
                "reward": 142.0
            },
            {
                "combination": "(-1, -1, -1, 1, -1, 1, 1, 1)",
                "reward": 112.0
            },
            {
                "combination": "(-1, -1, -1, 1, 1, -1, -1, -1)",
                "reward": 101.0
            },
            {
                "combination": "(-1, -1, -1, 1, 1, -1, -1, 1)",
                "reward": 110.0
            },
            {
                "combination": "(-1, -1, -1, 1, 1, -1, 1, -1)",
                "reward": 136.0
            },
            {
                "combination": "(-1, -1, -1, 1, 1, -1, 1, 1)",
                "reward": 106.0
            },
            {
                "combination": "(-1, -1, -1, 1, 1, 1, -1, -1)",
                "reward": 129.0
            },
            {
                "combination": "(-1, -1, -1, 1, 1, 1, -1, 1)",
                "reward": 138.0
            },
            {
                "combination": "(-1, -1, -1, 1, 1, 1, 1, -1)",
                "reward": 164.0
            },
            {
                "combination": "(-1, -1, -1, 1, 1, 1, 1, 1)",
                "reward": 134.0
            },
            {
                "combination": "(-1, -1, 1, -1, -1, -1, -1, -1)",
                "reward": 95.0
            },
            {
                "combination": "(-1, -1, 1, -1, -1, -1, -1, 1)",
                "reward": 104.0
            },
            {
                "combination": "(-1, -1, 1, -1, -1, -1, 1, -1)",
                "reward": 130.0
            },
            {
                "combination": "(-1, -1, 1, -1, -1, -1, 1, 1)",
                "reward": 100.0
            },
            {
                "combination": "(-1, -1, 1, -1, -1, 1, -1, -1)",
                "reward": 110.0
            },
            {
                "combination": "(-1, -1, 1, -1, -1, 1, -1, 1)",
                "reward": 119.0
            },
            {
                "combination": "(-1, -1, 1, -1, -1, 1, 1, -1)",
                "reward": 144.0
            },
            {
                "combination": "(-1, -1, 1, -1, -1, 1, 1, 1)",
                "reward": 115.0
            },
            {
                "combination": "(-1, -1, 1, -1, 1, -1, -1, -1)",
                "reward": 103.0
            },
            {
                "combination": "(-1, -1, 1, -1, 1, -1, -1, 1)",
                "reward": 112.0
            },
            {
                "combination": "(-1, -1, 1, -1, 1, -1, 1, -1)",
                "reward": 138.0
            },
            {
                "combination": "(-1, -1, 1, -1, 1, -1, 1, 1)",
                "reward": 108.0
            },
            {
                "combination": "(-1, -1, 1, -1, 1, 1, -1, -1)",
                "reward": 131.0
            },
            {
                "combination": "(-1, -1, 1, -1, 1, 1, -1, 1)",
                "reward": 140.0
            },
            {
                "combination": "(-1, -1, 1, -1, 1, 1, 1, -1)",
                "reward": 166.0
            },
            {
                "combination": "(-1, -1, 1, -1, 1, 1, 1, 1)",
                "reward": 136.0
            },
            {
                "combination": "(-1, -1, 1, 1, -1, -1, -1, -1)",
                "reward": 81.0
            },
            {
                "combination": "(-1, -1, 1, 1, -1, -1, -1, 1)",
                "reward": 90.0
            },
            {
                "combination": "(-1, -1, 1, 1, -1, -1, 1, -1)",
                "reward": 116.0
            },
            {
                "combination": "(-1, -1, 1, 1, -1, -1, 1, 1)",
                "reward": 86.0
            },
            {
                "combination": "(-1, -1, 1, 1, -1, 1, -1, -1)",
                "reward": 96.0
            },
            {
                "combination": "(-1, -1, 1, 1, -1, 1, -1, 1)",
                "reward": 105.0
            },
            {
                "combination": "(-1, -1, 1, 1, -1, 1, 1, -1)",
                "reward": 130.0
            },
            {
                "combination": "(-1, -1, 1, 1, -1, 1, 1, 1)",
                "reward": 101.0
            },
            {
                "combination": "(-1, -1, 1, 1, 1, -1, -1, -1)",
                "reward": 89.0
            },
            {
                "combination": "(-1, -1, 1, 1, 1, -1, -1, 1)",
                "reward": 98.0
            },
            {
                "combination": "(-1, -1, 1, 1, 1, -1, 1, -1)",
                "reward": 124.0
            },
            {
                "combination": "(-1, -1, 1, 1, 1, -1, 1, 1)",
                "reward": 94.0
            },
            {
                "combination": "(-1, -1, 1, 1, 1, 1, -1, -1)",
                "reward": 117.0
            },
            {
                "combination": "(-1, -1, 1, 1, 1, 1, -1, 1)",
                "reward": 126.0
            },
            {
                "combination": "(-1, -1, 1, 1, 1, 1, 1, -1)",
                "reward": 152.0
            },
            {
                "combination": "(-1, -1, 1, 1, 1, 1, 1, 1)",
                "reward": 122.0
            },
            {
                "combination": "(-1, 1, -1, -1, -1, -1, -1, -1)",
                "reward": 30
            },
            {
                "combination": "(-1, 1, -1, -1, -1, -1, -1, 1)",
                "reward": 39.0
            },
            {
                "combination": "(-1, 1, -1, -1, -1, -1, 1, -1)",
                "reward": 65.0
            },
            {
                "combination": "(-1, 1, -1, -1, -1, -1, 1, 1)",
                "reward": 35.0
            },
            {
                "combination": "(-1, 1, -1, -1, -1, 1, -1, -1)",
                "reward": 45.0
            },
            {
                "combination": "(-1, 1, -1, -1, -1, 1, -1, 1)",
                "reward": 54.0
            },
            {
                "combination": "(-1, 1, -1, -1, -1, 1, 1, -1)",
                "reward": 80.0
            },
            {
                "combination": "(-1, 1, -1, -1, -1, 1, 1, 1)",
                "reward": 50.0
            },
            {
                "combination": "(-1, 1, -1, -1, 1, -1, -1, -1)",
                "reward": 39.0
            },
            {
                "combination": "(-1, 1, -1, -1, 1, -1, -1, 1)",
                "reward": 48.0
            },
            {
                "combination": "(-1, 1, -1, -1, 1, -1, 1, -1)",
                "reward": 73.0
            },
            {
                "combination": "(-1, 1, -1, -1, 1, -1, 1, 1)",
                "reward": 44.0
            },
            {
                "combination": "(-1, 1, -1, -1, 1, 1, -1, -1)",
                "reward": 66.0
            },
            {
                "combination": "(-1, 1, -1, -1, 1, 1, -1, 1)",
                "reward": 75.0
            },
            {
                "combination": "(-1, 1, -1, -1, 1, 1, 1, -1)",
                "reward": 101.0
            },
            {
                "combination": "(-1, 1, -1, -1, 1, 1, 1, 1)",
                "reward": 71.0
            },
            {
                "combination": "(-1, 1, -1, 1, -1, -1, -1, -1)",
                "reward": 62.0
            },
            {
                "combination": "(-1, 1, -1, 1, -1, -1, -1, 1)",
                "reward": 71.0
            },
            {
                "combination": "(-1, 1, -1, 1, -1, -1, 1, -1)",
                "reward": 97.0
            },
            {
                "combination": "(-1, 1, -1, 1, -1, -1, 1, 1)",
                "reward": 67.0
            },
            {
                "combination": "(-1, 1, -1, 1, -1, 1, -1, -1)",
                "reward": 77.0
            },
            {
                "combination": "(-1, 1, -1, 1, -1, 1, -1, 1)",
                "reward": 86.0
            },
            {
                "combination": "(-1, 1, -1, 1, -1, 1, 1, -1)",
                "reward": 111.0
            },
            {
                "combination": "(-1, 1, -1, 1, -1, 1, 1, 1)",
                "reward": 82.0
            },
            {
                "combination": "(-1, 1, -1, 1, 1, -1, -1, -1)",
                "reward": 70.0
            },
            {
                "combination": "(-1, 1, -1, 1, 1, -1, -1, 1)",
                "reward": 79.0
            },
            {
                "combination": "(-1, 1, -1, 1, 1, -1, 1, -1)",
                "reward": 105.0
            },
            {
                "combination": "(-1, 1, -1, 1, 1, -1, 1, 1)",
                "reward": 75.0
            },
            {
                "combination": "(-1, 1, -1, 1, 1, 1, -1, -1)",
                "reward": 98.0
            },
            {
                "combination": "(-1, 1, -1, 1, 1, 1, -1, 1)",
                "reward": 107.0
            },
            {
                "combination": "(-1, 1, -1, 1, 1, 1, 1, -1)",
                "reward": 133.0
            },
            {
                "combination": "(-1, 1, -1, 1, 1, 1, 1, 1)",
                "reward": 103.0
            },
            {
                "combination": "(-1, 1, 1, -1, -1, -1, -1, -1)",
                "reward": 64.0
            },
            {
                "combination": "(-1, 1, 1, -1, -1, -1, -1, 1)",
                "reward": 73.0
            },
            {
                "combination": "(-1, 1, 1, -1, -1, -1, 1, -1)",
                "reward": 99.0
            },
            {
                "combination": "(-1, 1, 1, -1, -1, -1, 1, 1)",
                "reward": 69.0
            },
            {
                "combination": "(-1, 1, 1, -1, -1, 1, -1, -1)",
                "reward": 79.0
            },
            {
                "combination": "(-1, 1, 1, -1, -1, 1, -1, 1)",
                "reward": 88.0
            },
            {
                "combination": "(-1, 1, 1, -1, -1, 1, 1, -1)",
                "reward": 113.0
            },
            {
                "combination": "(-1, 1, 1, -1, -1, 1, 1, 1)",
                "reward": 84.0
            },
            {
                "combination": "(-1, 1, 1, -1, 1, -1, -1, -1)",
                "reward": 72.0
            },
            {
                "combination": "(-1, 1, 1, -1, 1, -1, -1, 1)",
                "reward": 81.0
            },
            {
                "combination": "(-1, 1, 1, -1, 1, -1, 1, -1)",
                "reward": 107.0
            },
            {
                "combination": "(-1, 1, 1, -1, 1, -1, 1, 1)",
                "reward": 77.0
            },
            {
                "combination": "(-1, 1, 1, -1, 1, 1, -1, -1)",
                "reward": 100.0
            },
            {
                "combination": "(-1, 1, 1, -1, 1, 1, -1, 1)",
                "reward": 109.0
            },
            {
                "combination": "(-1, 1, 1, -1, 1, 1, 1, -1)",
                "reward": 135.0
            },
            {
                "combination": "(-1, 1, 1, -1, 1, 1, 1, 1)",
                "reward": 105.0
            },
            {
                "combination": "(-1, 1, 1, 1, -1, -1, -1, -1)",
                "reward": 50.0
            },
            {
                "combination": "(-1, 1, 1, 1, -1, -1, -1, 1)",
                "reward": 59.0
            },
            {
                "combination": "(-1, 1, 1, 1, -1, -1, 1, -1)",
                "reward": 85.0
            },
            {
                "combination": "(-1, 1, 1, 1, -1, -1, 1, 1)",
                "reward": 55.0
            },
            {
                "combination": "(-1, 1, 1, 1, -1, 1, -1, -1)",
                "reward": 65.0
            },
            {
                "combination": "(-1, 1, 1, 1, -1, 1, -1, 1)",
                "reward": 74.0
            },
            {
                "combination": "(-1, 1, 1, 1, -1, 1, 1, -1)",
                "reward": 99.0
            },
            {
                "combination": "(-1, 1, 1, 1, -1, 1, 1, 1)",
                "reward": 70.0
            },
            {
                "combination": "(-1, 1, 1, 1, 1, -1, -1, -1)",
                "reward": 58.0
            },
            {
                "combination": "(-1, 1, 1, 1, 1, -1, -1, 1)",
                "reward": 67.0
            },
            {
                "combination": "(-1, 1, 1, 1, 1, -1, 1, -1)",
                "reward": 93.0
            },
            {
                "combination": "(-1, 1, 1, 1, 1, -1, 1, 1)",
                "reward": 63.0
            },
            {
                "combination": "(-1, 1, 1, 1, 1, 1, -1, -1)",
                "reward": 86.0
            },
            {
                "combination": "(-1, 1, 1, 1, 1, 1, -1, 1)",
                "reward": 95.0
            },
            {
                "combination": "(-1, 1, 1, 1, 1, 1, 1, -1)",
                "reward": 121.0
            },
            {
                "combination": "(-1, 1, 1, 1, 1, 1, 1, 1)",
                "reward": 91.0
            },
            {
                "combination": "(1, -1, -1, -1, -1, -1, -1, -1)",
                "reward": 51.0
            },
            {
                "combination": "(1, -1, -1, -1, -1, -1, -1, 1)",
                "reward": 60.0
            },
            {
                "combination": "(1, -1, -1, -1, -1, -1, 1, -1)",
                "reward": 86.0
            },
            {
                "combination": "(1, -1, -1, -1, -1, -1, 1, 1)",
                "reward": 56.0
            },
            {
                "combination": "(1, -1, -1, -1, -1, 1, -1, -1)",
                "reward": 65.0
            },
            {
                "combination": "(1, -1, -1, -1, -1, 1, -1, 1)",
                "reward": 75.0
            },
            {
                "combination": "(1, -1, -1, -1, -1, 1, 1, -1)",
                "reward": 100.0
            },
            {
                "combination": "(1, -1, -1, -1, -1, 1, 1, 1)",
                "reward": 70.0
            },
            {
                "combination": "(1, -1, -1, -1, 1, -1, -1, -1)",
                "reward": 59.0
            },
            {
                "combination": "(1, -1, -1, -1, 1, -1, -1, 1)",
                "reward": 68.0
            },
            {
                "combination": "(1, -1, -1, -1, 1, -1, 1, -1)",
                "reward": 94.0
            },
            {
                "combination": "(1, -1, -1, -1, 1, -1, 1, 1)",
                "reward": 64.0
            },
            {
                "combination": "(1, -1, -1, -1, 1, 1, -1, -1)",
                "reward": 87.0
            },
            {
                "combination": "(1, -1, -1, -1, 1, 1, -1, 1)",
                "reward": 96.0
            },
            {
                "combination": "(1, -1, -1, -1, 1, 1, 1, -1)",
                "reward": 122.0
            },
            {
                "combination": "(1, -1, -1, -1, 1, 1, 1, 1)",
                "reward": 92.0
            },
            {
                "combination": "(1, -1, -1, 1, -1, -1, -1, -1)",
                "reward": 82.0
            },
            {
                "combination": "(1, -1, -1, 1, -1, -1, -1, 1)",
                "reward": 92.0
            },
            {
                "combination": "(1, -1, -1, 1, -1, -1, 1, -1)",
                "reward": 117.0
            },
            {
                "combination": "(1, -1, -1, 1, -1, -1, 1, 1)",
                "reward": 87.0
            },
            {
                "combination": "(1, -1, -1, 1, -1, 1, -1, -1)",
                "reward": 97.0
            },
            {
                "combination": "(1, -1, -1, 1, -1, 1, -1, 1)",
                "reward": 106.0
            },
            {
                "combination": "(1, -1, -1, 1, -1, 1, 1, -1)",
                "reward": 132.0
            },
            {
                "combination": "(1, -1, -1, 1, -1, 1, 1, 1)",
                "reward": 102.0
            },
            {
                "combination": "(1, -1, -1, 1, 1, -1, -1, -1)",
                "reward": 91.0
            },
            {
                "combination": "(1, -1, -1, 1, 1, -1, -1, 1)",
                "reward": 100.0
            },
            {
                "combination": "(1, -1, -1, 1, 1, -1, 1, -1)",
                "reward": 126.0
            },
            {
                "combination": "(1, -1, -1, 1, 1, -1, 1, 1)",
                "reward": 96.0
            },
            {
                "combination": "(1, -1, -1, 1, 1, 1, -1, -1)",
                "reward": 119.0
            },
            {
                "combination": "(1, -1, -1, 1, 1, 1, -1, 1)",
                "reward": 128.0
            },
            {
                "combination": "(1, -1, -1, 1, 1, 1, 1, -1)",
                "reward": 154.0
            },
            {
                "combination": "(1, -1, -1, 1, 1, 1, 1, 1)",
                "reward": 124.0
            },
            {
                "combination": "(1, -1, 1, -1, -1, -1, -1, -1)",
                "reward": 85.0
            },
            {
                "combination": "(1, -1, 1, -1, -1, -1, -1, 1)",
                "reward": 94.0
            },
            {
                "combination": "(1, -1, 1, -1, -1, -1, 1, -1)",
                "reward": 119.0
            },
            {
                "combination": "(1, -1, 1, -1, -1, -1, 1, 1)",
                "reward": 90.0
            },
            {
                "combination": "(1, -1, 1, -1, -1, 1, -1, -1)",
                "reward": 99.0
            },
            {
                "combination": "(1, -1, 1, -1, -1, 1, -1, 1)",
                "reward": 108.0
            },
            {
                "combination": "(1, -1, 1, -1, -1, 1, 1, -1)",
                "reward": 134.0
            },
            {
                "combination": "(1, -1, 1, -1, -1, 1, 1, 1)",
                "reward": 104.0
            },
            {
                "combination": "(1, -1, 1, -1, 1, -1, -1, -1)",
                "reward": 93.0
            },
            {
                "combination": "(1, -1, 1, -1, 1, -1, -1, 1)",
                "reward": 102.0
            },
            {
                "combination": "(1, -1, 1, -1, 1, -1, 1, -1)",
                "reward": 128.0
            },
            {
                "combination": "(1, -1, 1, -1, 1, -1, 1, 1)",
                "reward": 98.0
            },
            {
                "combination": "(1, -1, 1, -1, 1, 1, -1, -1)",
                "reward": 121.0
            },
            {
                "combination": "(1, -1, 1, -1, 1, 1, -1, 1)",
                "reward": 130.0
            },
            {
                "combination": "(1, -1, 1, -1, 1, 1, 1, -1)",
                "reward": 156.0
            },
            {
                "combination": "(1, -1, 1, -1, 1, 1, 1, 1)",
                "reward": 126.0
            },
            {
                "combination": "(1, -1, 1, 1, -1, -1, -1, -1)",
                "reward": 71.0
            },
            {
                "combination": "(1, -1, 1, 1, -1, -1, -1, 1)",
                "reward": 80.0
            },
            {
                "combination": "(1, -1, 1, 1, -1, -1, 1, -1)",
                "reward": 105.0
            },
            {
                "combination": "(1, -1, 1, 1, -1, -1, 1, 1)",
                "reward": 76.0
            },
            {
                "combination": "(1, -1, 1, 1, -1, 1, -1, -1)",
                "reward": 85.0
            },
            {
                "combination": "(1, -1, 1, 1, -1, 1, -1, 1)",
                "reward": 94.0
            },
            {
                "combination": "(1, -1, 1, 1, -1, 1, 1, -1)",
                "reward": 120.0
            },
            {
                "combination": "(1, -1, 1, 1, -1, 1, 1, 1)",
                "reward": 90.0
            },
            {
                "combination": "(1, -1, 1, 1, 1, -1, -1, -1)",
                "reward": 79.0
            },
            {
                "combination": "(1, -1, 1, 1, 1, -1, -1, 1)",
                "reward": 88.0
            },
            {
                "combination": "(1, -1, 1, 1, 1, -1, 1, -1)",
                "reward": 114.0
            },
            {
                "combination": "(1, -1, 1, 1, 1, -1, 1, 1)",
                "reward": 84.0
            },
            {
                "combination": "(1, -1, 1, 1, 1, 1, -1, -1)",
                "reward": 107.0
            },
            {
                "combination": "(1, -1, 1, 1, 1, 1, -1, 1)",
                "reward": 116.0
            },
            {
                "combination": "(1, -1, 1, 1, 1, 1, 1, -1)",
                "reward": 142.0
            },
            {
                "combination": "(1, -1, 1, 1, 1, 1, 1, 1)",
                "reward": 112.0
            },
            {
                "combination": "(1, 1, -1, -1, -1, -1, -1, -1)",
                "reward": 64.0
            },
            {
                "combination": "(1, 1, -1, -1, -1, -1, -1, 1)",
                "reward": 74.0
            },
            {
                "combination": "(1, 1, -1, -1, -1, -1, 1, -1)",
                "reward": 99.0
            },
            {
                "combination": "(1, 1, -1, -1, -1, -1, 1, 1)",
                "reward": 69.0
            },
            {
                "combination": "(1, 1, -1, -1, -1, 1, -1, -1)",
                "reward": 79.0
            },
            {
                "combination": "(1, 1, -1, -1, -1, 1, -1, 1)",
                "reward": 88.0
            },
            {
                "combination": "(1, 1, -1, -1, -1, 1, 1, -1)",
                "reward": 114.0
            },
            {
                "combination": "(1, 1, -1, -1, -1, 1, 1, 1)",
                "reward": 84.0
            },
            {
                "combination": "(1, 1, -1, -1, 1, -1, -1, -1)",
                "reward": 73.0
            },
            {
                "combination": "(1, 1, -1, -1, 1, -1, -1, 1)",
                "reward": 82.0
            },
            {
                "combination": "(1, 1, -1, -1, 1, -1, 1, -1)",
                "reward": 108.0
            },
            {
                "combination": "(1, 1, -1, -1, 1, -1, 1, 1)",
                "reward": 78.0
            },
            {
                "combination": "(1, 1, -1, -1, 1, 1, -1, -1)",
                "reward": 101.0
            },
            {
                "combination": "(1, 1, -1, -1, 1, 1, -1, 1)",
                "reward": 110.0
            },
            {
                "combination": "(1, 1, -1, -1, 1, 1, 1, -1)",
                "reward": 136.0
            },
            {
                "combination": "(1, 1, -1, -1, 1, 1, 1, 1)",
                "reward": 106.0
            },
            {
                "combination": "(1, 1, -1, 1, -1, -1, -1, -1)",
                "reward": 96.0
            },
            {
                "combination": "(1, 1, -1, 1, -1, -1, -1, 1)",
                "reward": 105.0
            },
            {
                "combination": "(1, 1, -1, 1, -1, -1, 1, -1)",
                "reward": 131.0
            },
            {
                "combination": "(1, 1, -1, 1, -1, -1, 1, 1)",
                "reward": 101.0
            },
            {
                "combination": "(1, 1, -1, 1, -1, 1, -1, -1)",
                "reward": 111.0
            },
            {
                "combination": "(1, 1, -1, 1, -1, 1, -1, 1)",
                "reward": 120.0
            },
            {
                "combination": "(1, 1, -1, 1, -1, 1, 1, -1)",
                "reward": 146.0
            },
            {
                "combination": "(1, 1, -1, 1, -1, 1, 1, 1)",
                "reward": 116.0
            },
            {
                "combination": "(1, 1, -1, 1, 1, -1, -1, -1)",
                "reward": 105.0
            },
            {
                "combination": "(1, 1, -1, 1, 1, -1, -1, 1)",
                "reward": 114.0
            },
            {
                "combination": "(1, 1, -1, 1, 1, -1, 1, -1)",
                "reward": 140.0
            },
            {
                "combination": "(1, 1, -1, 1, 1, -1, 1, 1)",
                "reward": 110.0
            },
            {
                "combination": "(1, 1, -1, 1, 1, 1, -1, -1)",
                "reward": 133.0
            },
            {
                "combination": "(1, 1, -1, 1, 1, 1, -1, 1)",
                "reward": 142.0
            },
            {
                "combination": "(1, 1, -1, 1, 1, 1, 1, -1)",
                "reward": 167.0
            },
            {
                "combination": "(1, 1, -1, 1, 1, 1, 1, 1)",
                "reward": 138.0
            },
            {
                "combination": "(1, 1, 1, -1, -1, -1, -1, -1)",
                "reward": 98.0
            },
            {
                "combination": "(1, 1, 1, -1, -1, -1, -1, 1)",
                "reward": 107.0
            },
            {
                "combination": "(1, 1, 1, -1, -1, -1, 1, -1)",
                "reward": 133.0
            },
            {
                "combination": "(1, 1, 1, -1, -1, -1, 1, 1)",
                "reward": 103.0
            },
            {
                "combination": "(1, 1, 1, -1, -1, 1, -1, -1)",
                "reward": 113.0
            },
            {
                "combination": "(1, 1, 1, -1, -1, 1, -1, 1)",
                "reward": 122.0
            },
            {
                "combination": "(1, 1, 1, -1, -1, 1, 1, -1)",
                "reward": 148.0
            },
            {
                "combination": "(1, 1, 1, -1, -1, 1, 1, 1)",
                "reward": 118.0
            },
            {
                "combination": "(1, 1, 1, -1, 1, -1, -1, -1)",
                "reward": 107.0
            },
            {
                "combination": "(1, 1, 1, -1, 1, -1, -1, 1)",
                "reward": 116.0
            },
            {
                "combination": "(1, 1, 1, -1, 1, -1, 1, -1)",
                "reward": 142.0
            },
            {
                "combination": "(1, 1, 1, -1, 1, -1, 1, 1)",
                "reward": 112.0
            },
            {
                "combination": "(1, 1, 1, -1, 1, 1, -1, -1)",
                "reward": 135.0
            },
            {
                "combination": "(1, 1, 1, -1, 1, 1, -1, 1)",
                "reward": 144.0
            },
            {
                "combination": "(1, 1, 1, -1, 1, 1, 1, -1)",
                "reward": 169.0
            },
            {
                "combination": "(1, 1, 1, -1, 1, 1, 1, 1)",
                "reward": 140.0
            },
            {
                "combination": "(1, 1, 1, 1, -1, -1, -1, -1)",
                "reward": 84.0
            },
            {
                "combination": "(1, 1, 1, 1, -1, -1, -1, 1)",
                "reward": 93.0
            },
            {
                "combination": "(1, 1, 1, 1, -1, -1, 1, -1)",
                "reward": 119.0
            },
            {
                "combination": "(1, 1, 1, 1, -1, -1, 1, 1)",
                "reward": 89.0
            },
            {
                "combination": "(1, 1, 1, 1, -1, 1, -1, -1)",
                "reward": 99.0
            },
            {
                "combination": "(1, 1, 1, 1, -1, 1, -1, 1)",
                "reward": 108.0
            },
            {
                "combination": "(1, 1, 1, 1, -1, 1, 1, -1)",
                "reward": 134.0
            },
            {
                "combination": "(1, 1, 1, 1, -1, 1, 1, 1)",
                "reward": 104.0
            },
            {
                "combination": "(1, 1, 1, 1, 1, -1, -1, -1)",
                "reward": 93.0
            },
            {
                "combination": "(1, 1, 1, 1, 1, -1, -1, 1)",
                "reward": 102.0
            },
            {
                "combination": "(1, 1, 1, 1, 1, -1, 1, -1)",
                "reward": 128.0
            },
            {
                "combination": "(1, 1, 1, 1, 1, -1, 1, 1)",
                "reward": 98.0
            },
            {
                "combination": "(1, 1, 1, 1, 1, 1, -1, -1)",
                "reward": 121.0
            },
            {
                "combination": "(1, 1, 1, 1, 1, 1, -1, 1)",
                "reward": 130.0
            },
            {
                "combination": "(1, 1, 1, 1, 1, 1, 1, -1)",
                "reward": 155.0
            },
            {
                "combination": "(1, 1, 1, 1, 1, 1, 1, 1)",
                "reward": 126.0
            }
        ]
    }
}